AUTHORS
ChangeLog
MANIFEST.in
README.rst
requirements.txt
setup.cfg
setup.py
leonardo_newsletter/__init__.py
leonardo_newsletter/models.py
leonardo_newsletter/tasks.py
leonardo_newsletter/urls.py
leonardo_newsletter.egg-info/PKG-INFO
leonardo_newsletter.egg-info/SOURCES.txt
leonardo_newsletter.egg-info/dependency_links.txt
leonardo_newsletter.egg-info/not-zip-safe
leonardo_newsletter.egg-info/pbr.json
leonardo_newsletter.egg-info/top_level.txt
leonardo_newsletter/apps/__init__.py
leonardo_newsletter/apps/newsletter.py
leonardo_newsletter/migrations/__init__.py
leonardo_newsletter/templates/newsletter/base.html
leonardo_newsletter/templates/newsletter/newsletter_link_site.html
leonardo_newsletter/templates/newsletter/newsletter_link_unsubscribe.html
leonardo_newsletter/templates/widget/subscriptionform/default.html
leonardo_newsletter/widget/__init__.py
leonardo_newsletter/widget/subscriptionform/__init__.py
leonardo_newsletter/widget/subscriptionform/models.py
requirements/default.txt